trackerfw/__init__.py
trackerfw/handler.py
trackerfw/match_info.py
trackerfw/module.py
trackerfw/route.py
trackerfw/router.py
trackerfw/tracker_utils.py
trackerfw/webserver.py
trackerfw/certs/cert.pem
trackerfw/certs/key.pem
trackerfw/config/trackers.yml
trackerfw/handlers/__init__.py
trackerfw/handlers/bitly.py
trackerfw/handlers/click_tracker.py
trackerfw/handlers/dispatcher.py
trackerfw/handlers/subscribe.py
trackerfw/modules/__init__.py
trackerfw/modules/click_trackers.py
trackerfw/modules/share.py
trackerfw/modules/trackers.py
trackerfw-0.0.4.dist-info/DESCRIPTION.rst
trackerfw-0.0.4.dist-info/METADATA
trackerfw-0.0.4.dist-info/RECORD
trackerfw-0.0.4.dist-info/WHEEL
trackerfw-0.0.4.dist-info/entry_points.txt
trackerfw-0.0.4.dist-info/metadata.json
trackerfw-0.0.4.dist-info/top_level.txt
