Metadata-Version: 2.0
Name: trackerfw
Version: 0.0.4
Summary: TrackerFw - firewall for trackers
Home-page: https://github.com/PrivacySec/TrackerFw
Author: Dillen Meijboom
Author-email: info@dmeijboom.nl
License: UNKNOWN
Keywords: trackerfw tracker-fw anti-track ghostery
Platform: UNKNOWN
Classifier: Development Status :: 4 - Beta
Classifier: Intended Audience :: Developers
Classifier: Topic :: Software Development :: Build Tools
Classifier: License :: OSI Approved :: MIT License
Classifier: Programming Language :: Python :: 3.5
Classifier: Programming Language :: Python :: 3.6
Requires-Python: >=3.5
Requires-Dist: PyYAML
Requires-Dist: Jinja2
Requires-Dist: aiohttp
Requires-Dist: aiohttp-jinja2
